presentable/__init__.py
presentable/presentable.py
test/__init__.py
test/test_presentable.py
presentable-1.0.0.dist-info/LICENSE
presentable-1.0.0.dist-info/METADATA
presentable-1.0.0.dist-info/WHEEL
presentable-1.0.0.dist-info/top_level.txt
presentable-1.0.0.dist-info/RECORD
