Metadata-Version: 2.1
Name: presentable
Version: 1.0.0
Summary: Providing a Prettier Confusion Matrix for your Command Line
Home-page: https://github.com/JacksonBurns/presentable
Author: Jackson Burns
License: MIT
Classifier: Programming Language :: Python :: 3
License-File: LICENSE
Requires-Dist: numpy
Requires-Dist: tabulate
Requires-Dist: scikit-learn
Provides-Extra: dev
Requires-Dist: twine ; extra == 'dev'
Requires-Dist: build ; extra == 'dev'
